dnnets/__init__.py
dnnets/py.typed
dnnets/_lib/libdnnets.dylib
dnnets-0.2.1.dist-info/METADATA
dnnets-0.2.1.dist-info/WHEEL
dnnets-0.2.1.dist-info/licenses/LICENSE
dnnets-0.2.1.dist-info/RECORD
