Metadata-Version: 2.4
Name: dnnets
Version: 0.2.1
Summary: Running multilayer perceptrons on the CPU
Project-URL: Homepage, https://git.sr.ht/~hannes/dnnets
Project-URL: Documentation, https://hannesbraun.net/share/doc/dnnets/python/index.html
Project-URL: Repository, https://git.sr.ht/~hannes/dnnets
Project-URL: Changelog, https://git.sr.ht/~hannes/dnnets/refs
Author-email: Hannes Braun <hannes@hannesbraun.net>
License-Expression: LGPL-3.0-only
License-File: LICENSE
Keywords: Feedforward,Multilayer perceptron,Neural Network
Classifier: Development Status :: 4 - Beta
Classifier: Intended Audience :: Developers
Classifier: Programming Language :: Other
Classifier: Programming Language :: Python
Classifier: Topic :: Scientific/Engineering :: Artificial Intelligence
Classifier: Topic :: Software Development
Requires-Python: >=3.10
Provides-Extra: numpy
Requires-Dist: numpy>=2.0.0; extra == 'numpy'
